README.rst
setup.py
sentry_dingding/__init__.py
sentry_dingding/models.py
sentry_dingding_robot.egg-info/PKG-INFO
sentry_dingding_robot.egg-info/SOURCES.txt
sentry_dingding_robot.egg-info/dependency_links.txt
sentry_dingding_robot.egg-info/entry_points.txt
sentry_dingding_robot.egg-info/not-zip-safe
sentry_dingding_robot.egg-info/requires.txt
sentry_dingding_robot.egg-info/top_level.txt